aurora/__init__.py
aurora/general_helper_functions.py
aurora/config/__init__.py
aurora/config/config_creator.py
aurora/config/emtf_band_setup/__init__.py
aurora/config/emtf_band_setup/bs_256_26.cfg
aurora/config/emtf_band_setup/bs_256_29.cfg
aurora/config/emtf_band_setup/bs_six_level.cfg
aurora/config/emtf_band_setup/bs_test.cfg
aurora/config/emtf_band_setup/bs_test_fast.cfg
aurora/config/metadata/__init__.py
aurora/config/metadata/processing.py
aurora/pipelines/__init__.py
aurora/pipelines/feature_weights.py
aurora/pipelines/helpers.py
aurora/pipelines/process_mth5.py
aurora/pipelines/time_series_helpers.py
aurora/pipelines/transfer_function_helpers.py
aurora/pipelines/transfer_function_kernel.py
aurora/sandbox/__init__.py
aurora/sandbox/debug_mt_metadata_issue_85.py
aurora/sandbox/mth5_channel_summary_helpers.py
aurora/sandbox/mth5_helpers.py
aurora/sandbox/obspy_helpers.py
aurora/sandbox/plot_helpers.py
aurora/sandbox/triage_metadata.py
aurora/sandbox/io_helpers/__init__.py
aurora/sandbox/io_helpers/emtf_band_setup.py
aurora/sandbox/io_helpers/fdsn_dataset.py
aurora/sandbox/io_helpers/inventory_review.py
aurora/sandbox/io_helpers/make_mth5_helpers.py
aurora/sandbox/io_helpers/zfile_murphy.py
aurora/sandbox/io_helpers/garys_matlab_zfiles/matlab_z_file_reader.py
aurora/test_utils/__init__.py
aurora/test_utils/dataset_definitions.py
aurora/test_utils/mth5/__init__.py
aurora/test_utils/mth5/fc_helpers.py
aurora/test_utils/parkfield/__init__.py
aurora/test_utils/parkfield/calibration_helpers.py
aurora/test_utils/parkfield/make_parkfield_mth5.py
aurora/test_utils/parkfield/path_helpers.py
aurora/test_utils/synthetic/__init__.py
aurora/test_utils/synthetic/make_processing_configs.py
aurora/test_utils/synthetic/paths.py
aurora/test_utils/synthetic/plot_helpers_synthetic.py
aurora/test_utils/synthetic/processing_helpers.py
aurora/test_utils/synthetic/rms_helpers.py
aurora/test_utils/synthetic/triage.py
aurora/time_series/__init__.py
aurora-0.5.2.dist-info/licenses/LICENSE
aurora-0.5.2.dist-info/METADATA
aurora-0.5.2.dist-info/WHEEL
aurora-0.5.2.dist-info/top_level.txt
aurora-0.5.2.dist-info/RECORD
