Metadata-Version: 2.4
Name: aurora
Version: 0.5.2
Summary: Processing Codes for Magnetotelluric Data
Author-email: Karl Kappler <karl.kappler@berkeley.edu>
License: MIT license
Project-URL: Homepage, https://github.com/simpeg/aurora
Keywords: aurora
Classifier: Development Status :: 2 - Pre-Alpha
Classifier: Intended Audience :: Developers
Classifier: License :: OSI Approved :: MIT License
Classifier: Natural Language :: English
Classifier: Programming Language :: Python :: 3
Classifier: Programming Language :: Python :: 3.8
Classifier: Programming Language :: Python :: 3.9
Classifier: Programming Language :: Python :: 3.10
Classifier: Programming Language :: Python :: 3.11
Requires-Python: >=3.8
License-File: LICENSE
Requires-Dist: mth5
Requires-Dist: numba
Requires-Dist: obspy
Requires-Dist: psutil
Provides-Extra: test
Requires-Dist: pytest>=3; extra == "test"
Requires-Dist: pytest-runner; extra == "test"
Provides-Extra: dev
Requires-Dist: black; extra == "dev"
Requires-Dist: flake8; extra == "dev"
Requires-Dist: ipython; extra == "dev"
Requires-Dist: nbsphinx; extra == "dev"
Requires-Dist: numpydoc; extra == "dev"
Requires-Dist: papermill; extra == "dev"
Requires-Dist: pre-commit; extra == "dev"
Requires-Dist: pytest; extra == "dev"
Requires-Dist: pytest-cov; extra == "dev"
Requires-Dist: toml; extra == "dev"
Requires-Dist: sphinx_gallery; extra == "dev"
Requires-Dist: sphinx_rtd_theme; extra == "dev"
Dynamic: license-file
